{
  "timeline": [
    {
      "id": 1,
      "time": "2026-03-24T04:45:00Z",
      "sport": "nba",
      "type": "game",
      "title": "🏀 活塞 vs 湖人：东西部榜首对话！",
      "description": "活塞（51-19）主场迎战湖人（46-25），东部第1与西部第2的巅峰对决，丹尼斯与唐西奇火力全开。",
      "importance": "high"
    },
    {
      "id": 2,
      "time": "2026-03-24T04:45:00Z",
      "sport": "nba",
      "type": "game",
      "title": "🏀 雷霆 vs 76人：西部第1强势碾压！",
      "description": "雷霆（56-15）客场挑战76人（39-32），吉尔杰斯-亚历山大场均31.6分领衔，西部第1势不可挡。",
      "importance": "high"
    },
    {
      "id": 3,
      "time": "2026-03-24T04:45:00Z",
      "sport": "nba",
      "type": "game",
      "title": "🏀 马刺 vs 热火：文班亚马对飙阿德巴约",
      "description": "马刺（53-18）客场挑战热火（38-33），文班亚马11.1篮板压制阿德巴约，西部第3志在必得。",
      "importance": "high"
    },
    {
      "id": 4,
      "time": "2026-03-24T04:45:00Z",
      "sport": "nba",
      "type": "standings",
      "title": "📊 NBA最新排名：活塞雷霆马刺领跑，湖人紧追",
      "description": "西部：雷霆56-15第1、马刺53-18第2、湖人46-25第3。东部：活塞51-19第1、凯尔特人领跑。",
      "importance": "medium"
    },
    {
      "id": 5,
      "time": "2026-03-24T04:45:00Z",
      "sport": "soccer",
      "sport": "soccer",
      "type": "game",
      "title": "⚽ 格拉纳达 vs 拉科鲁尼亚：西班牙德比1-0领先",
      "description": "西班牙足球甲级联赛，格拉纳达主场1-0领先拉科鲁尼亚，上半场激烈对抗，下半场悬念待续。",
      "importance": "medium"
    },
    {
      "id": 6,
      "time": "2026-03-24T04:45:00Z",
      "sport": "soccer",
      "type": "game",
      "title": "🌍 非洲女足杯：印度女足7-0狂胜阿巴战士",
      "description": "国际友谊赛，印度女足主场7-0大胜尼日利亚阿巴战士，进攻火力全开，防线固若金汤。",
      "importance": "low"
    },
    {
      "id": 7,
      "time": "2026-03-24T04:45:00Z",
      "sport": "soccer",
      "type": "game",
      "title": "⚽ 阿根廷足球甲级联赛：多场焦点战进行中",
      "description": "阿根廷甲级联赛多场比赛同时进行，本轮争夺积分激烈，各队为季后赛名额奋力冲刺。",
      "importance": "medium"
    },
    {
      "id": 8,
      "time": "2026-03-24T04:45:00Z",
      "sport": "tennis",
      "type": "game",
      "title": "🎾 迈阿密公开赛：女单第4轮激战进行中",
      "description": "WTA 1000迈阿密站女单第4轮，多场高质量对决同时开打，各路好手向半决赛发起冲击。",
      "importance": "high"
    },
    {
      "id": 9,
      "time": "2026-03-24T04:45:00Z",
      "sport": "tennis",
      "type": "game",
      "title": "🎾 迈阿密公开赛：男单第3轮精彩纷呈",
      "description": "ATP 1000迈阿密站男单第3轮，多位种子选手激烈对阵，争夺8强席位的竞争白热化。",
      "importance": "high"
    },
    {
      "id": 10,
      "time": "2026-03-24T04:45:00Z",
      "sport": "tennis",
      "type": "game",
      "title": "🎾 迈阿密公开赛：混双第1轮开战",
      "description": "ATP/WTA混双赛事第1轮，多对组合在不同球场同时出战，为争夺冠军积分而奋力拼搏。",
      "importance": "medium"
    }
  ],
  "lastUpdated": "2026-03-24T04:45:00Z",
  "sources": {
    "nba": "ESPN NBA",
    "soccer": "ESPN FC",
    "tennis": "ESPN Tennis"
  }
}
